MANIFEST.in
README.txt
setup.py
collective/__init__.py
collective.ptg.contentleadimage.egg-info/PKG-INFO
collective.ptg.contentleadimage.egg-info/SOURCES.txt
collective.ptg.contentleadimage.egg-info/dependency_links.txt
collective.ptg.contentleadimage.egg-info/entry_points.txt
collective.ptg.contentleadimage.egg-info/namespace_packages.txt
collective.ptg.contentleadimage.egg-info/not-zip-safe
collective.ptg.contentleadimage.egg-info/requires.txt
collective.ptg.contentleadimage.egg-info/top_level.txt
collective/ptg/__init__.py
collective/ptg/contentleadimage/__init__.py
collective/ptg/contentleadimage/adapters.py
collective/ptg/contentleadimage/configure.zcml
collective/ptg/contentleadimage/interfaces.py
collective/ptg/contentleadimage/version.txt
collective/ptg/contentleadimage/tests/__init__.py
collective/ptg/contentleadimage/tests/test_41x41.jpg
collective/ptg/contentleadimage/tests/test_adapter.py
docs/HISTORY.txt
docs/INSTALL.txt
docs/LICENSE.GPL
docs/LICENSE.txt