Metadata-Version: 1.1
Name: collective.ptg.contentleadimage
Version: 1.0
Summary: Display also contentleadimages
Home-page: http://github.com/collective/collective.plonetruegallery
Author: Ales Zabala Alava (Shagi)
Author-email: shagi@gisa-elkartea.org
License: GPL
Platform: UNKNOWN
Classifier: Framework :: Plone
Classifier: Programming Language :: Python
Classifier: License :: OSI Approved :: GNU General Public License v3 or later (GPLv3+)
